b_cfn_custom_userpool_authorizer/__init__.py
b_cfn_custom_userpool_authorizer/user_pool_custom_authorizer.py
b_cfn_custom_userpool_authorizer/user_pool_custom_authorizer_function.py
b_cfn_custom_userpool_authorizer/config/__init__.py
b_cfn_custom_userpool_authorizer/config/user_pool_config.py
b_cfn_custom_userpool_authorizer/config/user_pool_ssm_config.py
b_cfn_custom_userpool_authorizer/source/__init__.py
b_cfn_custom_userpool_authorizer/source/auth_exception.py
b_cfn_custom_userpool_authorizer/source/index.py
b_cfn_custom_userpool_authorizer/source/policy_document.py
b_cfn_custom_userpool_authorizer/source/token_verification.py
b_cfn_custom_userpool_authorizer/source/user_pool_resolver.py
b_cfn_custom_userpool_authorizer_test/integration/__init__.py
b_cfn_custom_userpool_authorizer_test/integration/app.py
b_cfn_custom_userpool_authorizer_test/integration/conftest.py
b_cfn_custom_userpool_authorizer_test/integration/infra_create.py
b_cfn_custom_userpool_authorizer_test/integration/infra_destroy.py
b_cfn_custom_userpool_authorizer_test/integration/manager.py
b_cfn_custom_userpool_authorizer_test/integration/fixtures/__init__.py
b_cfn_custom_userpool_authorizer_test/integration/fixtures/access_token.py
b_cfn_custom_userpool_authorizer_test/integration/infrastructure/__init__.py
b_cfn_custom_userpool_authorizer_test/integration/infrastructure/api_stack.py
b_cfn_custom_userpool_authorizer_test/integration/infrastructure/authorized_endpoint_stack.py
b_cfn_custom_userpool_authorizer_test/integration/infrastructure/main_stack.py
b_cfn_custom_userpool_authorizer_test/integration/infrastructure/user_pool_stack.py
b_cfn_custom_userpool_authorizer_test/integration/tests/__init__.py
b_cfn_custom_userpool_authorizer_test/integration/tests/test_authorizer_allow.py
b_cfn_custom_userpool_authorizer_test/integration/tests/test_authorizer_deny.py
b_cfn_custom_userpool_authorizer_test/integration/util/__init__.py
b_cfn_custom_userpool_authorizer_test/integration/util/urlsafe_json.py
b_cfn_custom_userpool_authorizer-2.0.0.dist-info/LICENSE
b_cfn_custom_userpool_authorizer-2.0.0.dist-info/METADATA
b_cfn_custom_userpool_authorizer-2.0.0.dist-info/WHEEL
b_cfn_custom_userpool_authorizer-2.0.0.dist-info/top_level.txt
b_cfn_custom_userpool_authorizer-2.0.0.dist-info/RECORD
