Metadata-Version: 2.1
Name: b-cfn-custom-userpool-authorizer
Version: 2.0.0
Summary: Package that enables deployment of AWS CDK stacks in parallel.
Home-page: https://github.com/biomapas/B.CfnCustomUserPoolAuthorizer.git
License: Apache License 2.0
Keywords: AWS Cognito UserPool Authorizer
Classifier: Programming Language :: Python :: 3
Classifier: Operating System :: OS Independent
License-File: LICENSE
Requires-Dist: python-jose (>=3.3.0)
Requires-Dist: b-lambda-layer-common (<5.0.0,>=4.0.0)
Requires-Dist: b-cfn-lambda-layer (<4.0.0,>=3.0.0)
Requires-Dist: b-cfn-lambda-integration (<2.0.0,>=1.0.0)
Requires-Dist: aws-cdk-lib (<3.0.0,>=2.0.0)
Requires-Dist: aws-cdk-constructs (<3.0.0,>=2.0.0)
